eckit/__init__.py
eckit/_eckit.cpython-310-aarch64-linux-gnu.so
eckit/geo/__init__.py
eckit/geo/_eckit_geo.cpython-310-aarch64-linux-gnu.so
eckit-1.32.4.8.dist-info/licenses/LICENSE
eckit-1.32.4.8.dist-info/METADATA
eckit-1.32.4.8.dist-info/WHEEL
eckit-1.32.4.8.dist-info/top_level.txt
eckit-1.32.4.8.dist-info/RECORD
