Metadata-Version: 2.4
Name: eckit
Version: 1.32.4.8
Summary: Don't use this
Author-email: "European Centre for Medium-Range Weather Forecasts (ECMWF)" <software.support@ecmwf.int>
License-Expression: Apache-2.0
Classifier: Development Status :: 3 - Alpha
Classifier: Intended Audience :: Developers
Classifier: Programming Language :: Python :: 3.10
Classifier: Programming Language :: Python :: 3.11
Classifier: Programming Language :: Cython
Classifier: Programming Language :: Python :: Implementation :: CPython
Classifier: Operating System :: POSIX :: Linux
Classifier: Operating System :: MacOS
Classifier: Topic :: Scientific/Engineering
Requires-Python: >=3.9
License-File: LICENSE
Requires-Dist: findlibs
Requires-Dist: pyyaml
Requires-Dist: eckitlib==1.32.4.8
Dynamic: license-file
Dynamic: requires-dist
